{
  "id": "45067419f9079312",
  "name": "zip",
  "domain": "programming",
  "entry_type": "command",
  "description": "Create zip archives",
  "position": [
    0.2,
    0.0,
    -0.7365278717717586,
    0.0,
    0.3122926417694852,
    0.0,
    0.0,
    0.0
  ],
  "keywords": [
    "bash",
    "shell",
    "command",
    "zip",
    "compress",
    "archive"
  ],
  "metadata": {
    "syntax": "zip archive.zip <files>",
    "example": "zip -r archive.zip folder/",
    "flags": "-r (recursive)"
  },
  "created_at": "2025-12-15T08:42:26.907088",
  "updated_at": "2025-12-15T11:49:02.879052",
  "version": 1
}