{
  "id": "339b1f7da842767b",
  "name": "sorted",
  "domain": "programming",
  "entry_type": "function",
  "description": "Return sorted list from iterable",
  "position": [
    0.2,
    0.0,
    0.0,
    0.0,
    0.0,
    0.0,
    0.0,
    0.0
  ],
  "keywords": [
    "sort",
    "order",
    "arrange",
    "ascending",
    "descending"
  ],
  "metadata": {
    "syntax": "sorted(iterable, key=None, reverse=False)",
    "example": "sorted_list = sorted(my_list)"
  },
  "created_at": "2025-12-14T19:06:00.269099",
  "updated_at": "2025-12-15T11:58:18.170758",
  "version": 1
}