{
  "id": "9b5a3e59b0f104ca",
  "name": "tr",
  "domain": "programming",
  "entry_type": "command",
  "description": "Translate or delete characters",
  "position": [
    0.2,
    0.0,
    -0.8,
    0.0,
    0.0,
    0.0,
    0.0,
    0.0
  ],
  "keywords": [
    "bash",
    "shell",
    "command",
    "translate",
    "replace",
    "characters",
    "tr",
    "convert"
  ],
  "metadata": {
    "syntax": "tr <set1> <set2>",
    "example": "echo 'hello' | tr 'a-z' 'A-Z'",
    "flags": "-d (delete), -s (squeeze)"
  },
  "created_at": "2025-12-15T08:42:26.904234",
  "updated_at": "2025-12-15T11:58:18.172440",
  "version": 1
}